product_catalog_mcp/__init__.py
product_catalog_mcp/server.py
product_catalog_mcp-0.1.0.dist-info/METADATA
product_catalog_mcp-0.1.0.dist-info/WHEEL
product_catalog_mcp-0.1.0.dist-info/entry_points.txt
product_catalog_mcp-0.1.0.dist-info/RECORD
