Metadata-Version: 2.4
Name: product-catalog-mcp
Version: 0.1.0
Summary: MCP server for querying product catalog data
Project-URL: Homepage, https://github.com/yourusername/product-catalog-mcp
Project-URL: Repository, https://github.com/yourusername/product-catalog-mcp
Author-email: Your Name <your.email@example.com>
License: MIT
Keywords: fastmcp,mcp,product-catalog
Classifier: Development Status :: 4 - Beta
Classifier: Intended Audience :: Developers
Classifier: License :: OSI Approved :: MIT License
Classifier: Programming Language :: Python :: 3
Classifier: Programming Language :: Python :: 3.10
Classifier: Programming Language :: Python :: 3.11
Classifier: Programming Language :: Python :: 3.12
Requires-Python: >=3.10
Requires-Dist: fastmcp>=0.1.0
